crosstab/__init__.py
crosstab/crosstab.py
crosstab-0.0.15.dist-info/licenses/LICENSE
crosstab-0.0.15.dist-info/METADATA
crosstab-0.0.15.dist-info/WHEEL
crosstab-0.0.15.dist-info/entry_points.txt
crosstab-0.0.15.dist-info/top_level.txt
crosstab-0.0.15.dist-info/RECORD
