Metadata-Version: 2.4
Name: crosstab
Version: 0.0.15
Summary: Rearrange data from a normalized CSV format to a crosstabulated format, with styling.
Author-email: Caleb Grant <grantcaleb22@gmail.com>
License:                     GNU GENERAL PUBLIC LICENSE
Project-URL: Homepage, https://crosstab.readthedocs.io
Project-URL: Repository, https://github.com/geocoug/crosstab
Project-URL: Issues, https://github.com/geocoug/crosstab/issues
Keywords: crosstab,xtab,crosstabulate,crosstabulation,pivot,pivot table,pivot-table,table
Classifier: Programming Language :: Python :: 3
Classifier: Programming Language :: Python :: 3.10
Classifier: Programming Language :: Python :: 3.11
Classifier: Programming Language :: Python :: 3.12
Classifier: Programming Language :: Python :: 3.13
Classifier: Operating System :: OS Independent
Classifier: Intended Audience :: Developers
Classifier: Topic :: Software Development :: Libraries :: Python Modules
Requires-Python: <3.14,>=3.10
License-File: LICENSE
Requires-Dist: openpyxl
Dynamic: license-file
